simulations/stochastic_system/hdp.v
`timescale 1ns / 1ps

module hdp (
    input [19:0] ciphertext,
    input [10:0] ct_modulus,   // ciphertext modulus = q
    input [8:0] pt_modulus,   // plaintext modulus = p
    output [7:0] res
    );
    
    reg[19:0] res_i;
    
    // p and q have to be consistent for all HEP/HDP slices
    // generating a public key can be any value from 0 to q-1
    
    // s needs to be consistent but is abstracted away for demonstration purposes
    // in theory all modules generate a secret key but assume they all agree on 7
    parameter secret_key = 7;
    reg[1:0] delta_shift = 2; // divide by four means shifting 2 places
    
    // determine the final result
    always @(*) begin
        // first compute b - as mod q
        // b = ciphertext[9:0]
        // a = ciphertext[19:10]
        // s = secret key
        res_i = (ciphertext[9:0] - (ciphertext[19:10] * secret_key)) % ct_modulus;
        res_i = res_i >> delta_shift; // final division to decrypt
    end
    
    assign res = res_i[7:0];
endmodule

simulations/tfhe_system/ct_adder.v
`timescale 1ns / 1ps

module ct_adder (
    input [19:0] ct1,
    input [19:0] ct2,
    output [19:0] ct_sum
    );
    
    // adding ciphertexts as shown
    // there's no need to carry since
    // a and b are always bounded by q = 256
    assign ct_sum = {ct1[19:10] + ct2[19:10], ct1[9:0] + ct2[9:0]};
endmodule

hep.v
`timescale 1ns / 1ps

module hep (
    input [7:0] pixel_byte,   // input byte
    input [9:0] public_key,   // public key = a
    input [10:0] ct_modulus,   // ciphertext modulus = q
    input [8:0] pt_modulus,   // plaintext modulus = p
    input error,
    output [19:0] ciphertext
    );
    // p and q have to be consistent for all HEP/HDP slices
    // generating a public key can be any value from 0 to q-1
    
    // s needs to be consistent but is abstracted away for demonstration purposes
    // in theory all modules generate a secret key but assume they all agree on 7
    parameter secret_key = 7;
    wire [2:0] delta = 4;
    
    reg [9:0] b;

    // calculate b using your public key
    always @(*) begin
        b = (public_key * secret_key) + (delta * pixel_byte) + error;
    end
    
    // do final assignments
    assign ciphertext[19:10] = public_key;
    assign ciphertext[9:0] = b;
    
endmodule

tfhe_processor_slice.v
`timescale 1ns / 1ps

// this module increases brightness of a grayscale image
module tfhe_processor_slice (
  input [7:0] byte1, // streamed in image byte
  input [9:0] public_key1, // random number 
  input [7:0] byte2, // represents some constant brightness
  input [9:0] public_key2, // random number
  output[7:0] res
    );

  wire [19:0] ct1, ct2, ct_sum;
  wire [10:0] ct_modulus = 11'd1024; // example ct (q) - 11 bits to hold 1024
  wire [8:0] pt_modulus = 9'd256;    // example pt (p) - 9 bits to hold 256

  // secret key is abstracted away from hep1, hep2, and decryptor modules
  // in the future the public keys will be created using RNGs but input
  // some random number between 0 and q-1 for now
  hep hep1 (
    .pixel_byte(byte1),   
    .public_key(public_key1), // random number
    .ct_modulus(ct_modulus),  
    .pt_modulus(pt_modulus),   
    .error(1'b1), // introduce error to both, e < q/2p or e < 2
    .ciphertext(ct1)
  );

  hep hep2 (
    .pixel_byte(byte2),
    .public_key(public_key2), // random number
    .ct_modulus(ct_modulus),  
    .pt_modulus(pt_modulus),   
    .error(1'b1), // add as much error to increase security and test strength
    .ciphertext(ct2)
  );

  ct_adder ct_addr (
    .ct1(ct1),
    .ct2(ct2),
    .ct_sum(ct_sum)
  );

  hdp decryptor (
    .ciphertext(ct_sum),
    .ct_modulus(ct_modulus),
    .pt_modulus(pt_modulus),
    .res(res)
  );

endmodule

simulations/stochastic_system/lfsr.v
`timescale 1ns / 1ps

module lfsr (
    input wire clk,
    input wire [9:0] seed,
    input wire rst_n,
    output wire [9:0] lfsr_out
);

reg [9:0] lfsr_reg;

// maximal-length LFSR polynomial: x^10 + x^7 + 1
wire feedback_bit;
assign feedback_bit = lfsr_reg[9] ^ lfsr_reg[6];

always @(posedge clk or negedge rst_n) begin
    if (!rst_n) begin
        // use non-zero seed; if seed is 0, use default
        lfsr_reg <= (seed == 10'b0) ? 10'b1 : seed;
    end else begin
        lfsr_reg <= {feedback_bit, lfsr_reg[9:1]};
    end
end

assign lfsr_out = lfsr_reg;

endmodule

simulations/tfhe_system/image_controller.v
`timescale 1ns / 1ps

module image_controller (
    input clk,              
    input rst_n,
    input [7:0] brightness,
    output hsync,
    output vsync,
    output [3:0] red,
    output [3:0] green,
    output [3:0] blue
);

    localparam H_DISPLAY = 640;
    localparam H_FRONT   = 16;
    localparam H_SYNC    = 96;
    localparam H_BACK    = 48;
    localparam H_TOTAL   = 800;

    localparam V_DISPLAY = 480;
    localparam V_FRONT   = 10;
    localparam V_SYNC    = 2;
    localparam V_BACK    = 33;
    localparam V_TOTAL   = 525;

    reg [1:0] clk_div;
    reg pixel_clk;
    always @(posedge clk or negedge rst_n) begin
        if (!rst_n) begin
            clk_div <= 0;
            pixel_clk <= 0;
        end else begin
            clk_div <= clk_div + 1;
            if (clk_div == 1) begin
                clk_div <= 0;
                pixel_clk <= ~pixel_clk;
            end
        end
    end

    reg [9:0] h_count, v_count;
    always @(posedge pixel_clk or negedge rst_n) begin
        if (!rst_n) begin
            h_count <= 0;
            v_count <= 0;
        end else begin
            if (h_count == H_TOTAL-1) begin
                h_count <= 0;
                if (v_count == V_TOTAL-1)
                    v_count <= 0;
                else
                    v_count <= v_count + 1;
            end else begin
                h_count <= h_count + 1;
            end
        end
    end

    assign hsync = ~((h_count >= H_DISPLAY + H_FRONT) && 
                     (h_count < H_DISPLAY + H_FRONT + H_SYNC));
    assign vsync = ~((v_count >= V_DISPLAY + V_FRONT) &&
                     (v_count < V_DISPLAY + V_FRONT + V_SYNC));

    wire display_enable = (h_count < H_DISPLAY) && (v_count < V_DISPLAY);


    (* ram_style = "block" *) reg [7:0] image_rom [0:4095];
    initial $readmemh("image_data.mem", image_rom);


    (* ram_style = "block" *) reg [7:0] processed_image [0:4095];

    reg [11:0] process_addr;
    reg processing_done;
    reg [2:0] state;

    localparam IDLE    = 3'd0;
    localparam PROCESS = 3'd1;
    localparam DISPLAY = 3'd2;

    wire [9:0] public_key1, public_key2;
    wire [7:0] current_pixel = image_rom[process_addr];
    wire [7:0] processed_pixel;

    lfsr lfsr1 (.clk(clk), .rst_n(rst_n), .seed(10'b1010101010), .lfsr_out(public_key1));
    lfsr lfsr2 (.clk(clk), .rst_n(rst_n), .seed(10'b0101010101), .lfsr_out(public_key2));

    tfhe_processor_slice tfhe (
        .byte1(current_pixel),
        .byte2(brightness),
        .public_key1(public_key1),
        .public_key2(public_key2),
        .res(processed_pixel)
    );

    always @(posedge clk or negedge rst_n) begin
        if (!rst_n) begin
            state <= IDLE;
            process_addr <= 0;
            processing_done <= 0;
        end else begin
            case (state)
                IDLE: begin
                    process_addr <= 0;
                    processing_done <= 0;
                    state <= PROCESS;
                end
                PROCESS: begin
                    processed_image[process_addr] <= processed_pixel;
                    if (process_addr == 4095) begin
                        state <= DISPLAY;
                        processing_done <= 1;
                    end else begin
                        process_addr <= process_addr + 1;
                    end
                end
                DISPLAY: state <= DISPLAY;
            endcase
        end
    end

    wire in_image_area = (h_count < 512) && (v_count < 480);  
    
    wire [5:0] img_x = h_count[8:3]; 
    wire [5:0] img_y = v_count[8:3];  
    
    wire [11:0] img_addr = (img_y * 64) + img_x;

    wire [7:0] display_pixel = image_rom[img_addr];
    
    wire [3:0] gray_value = display_pixel[7:4];

    // final rgb assignments
    assign red   = (display_enable && in_image_area) ? gray_value : 4'h0;
    assign green = (display_enable && in_image_area) ? gray_value : 4'h0;
    assign blue  = (display_enable && in_image_area) ? gray_value : 4'h0;

endmodule

simulations/tfhe_system/image_controller_tb.v
`timescale 1ns / 1ps

module image_controller_tb;

    reg clk;
    reg rst_n;
    reg [7:0] brightness;
    
    wire hsync;
    wire vsync;
    wire [3:0] red;
    wire [3:0] green;
    wire [3:0] blue;

    // instantiate the unit under test
    image_controller uut (
        .clk(clk),
        .rst_n(rst_n),
        .brightness(brightness),
        .hsync(hsync),
        .vsync(vsync),
        .red(red),
        .green(green),
        .blue(blue)
    );

    // make 100MHz clock
    initial begin
        clk = 0;
        forever #5 clk = ~clk;  
    end

    // test variables
    integer i;
    integer non_zero_count;
    integer frame_count;
    
    integer dump_file;
    
    task show_pixel;
        input [11:0] addr;
        begin
            $display("Pixel at address %d:", addr);
            $display("  Original:  0x%02h (%3d)", uut.image_rom[addr], uut.image_rom[addr]);
            $display("  Processed: 0x%02h (%3d)", uut.processed_image[addr], uut.processed_image[addr]);
            $display("  Difference: +0x%02h (+%3d)", 
                     uut.processed_image[addr] - uut.image_rom[addr],
                     uut.processed_image[addr] - uut.image_rom[addr]);
        end
    endtask

    initial begin
        rst_n = 0;
        brightness = 8'h0F;  // add 0x0F to all ROM values
        non_zero_count = 0;
        frame_count = 0;
        
        // create vcd dump for waveform viewing in python
        $dumpfile("image_controller_tb.vcd");
        $dumpvars(0,
            image_controller_tb.uut.hsync,
            image_controller_tb.uut.vsync,
            image_controller_tb.uut.red,
            image_controller_tb.uut.green,
            image_controller_tb.uut.blue,
            image_controller_tb.uut.display_enable
        );

        
        // reset pulse
        #100;
        rst_n = 1;
        #100;
        

        $display("\n========================================");
        $display("Test 1: Verifying ROM Contents");
        $display("========================================");
        
        // wait a bit for initialization
        #1000;
        
        $display("\nAll ROM entries:");
        for (i = 0; i < 4096; i = i + 1) begin
            $display("ROM[%4d] = 0x%02h", i, uut.image_rom[i]);
        end
        
        // count how many non-zero entries exist
        non_zero_count = 0;
        for (i = 0; i < 200; i = i + 1) begin
            if (uut.image_rom[i] != 8'h00) begin
                non_zero_count = non_zero_count + 1;
            end
        end
        
        $display("\nNon-zero ROM entries: %d / 4096", non_zero_count);
        if (non_zero_count == 0) begin
            $display("WARNING: ROM appears to be empty! Check image_data.mem file.");
        end else begin
            $display("ROM loaded successfully with data.");
        end
        
        $display("\n========================================");
        $display("Test 2: Monitoring TFHE Processing");
        $display("========================================");
        $display("Brightness value: 0x%02h (adding 0x0F to each pixel)", brightness);
        
        // monitor state machine
        $display("\nInitial state: %d", uut.state);
        $display("Processing address: %d", uut.process_addr);
        
        // wait for processing to complete
        wait(uut.processing_done == 1'b1);
        $display("\nProcessing completed!");
        $display("Final state: %d", uut.state);
        
        // check some processed pixels
        $display("\nFirst 10 processed pixels (Original + 0x0F):");
        for (i = 0; i < 10; i = i + 1) begin
            $display("Processed[%4d] = 0x%02h (Original: 0x%02h, Expected: 0x%02h)", 
                     i, uut.processed_image[i], uut.image_rom[i], 
                     (uut.image_rom[i] + brightness) & 8'hFF);
        end
        
        $display("\n--- Using show_pixel task ---");
        show_pixel(0);      // first pixel
        $display("CT1  = %020b", uut.tfhe.ct1);
        $display("CT2  = %020b", uut.tfhe.ct2);
        $display("SUM  = %020b", uut.tfhe.ct_sum);
        $display("");
        show_pixel(74);    // random middle pixel
        $display("");
        show_pixel(2047);   // center of image (32, 31)
        $display("");
        show_pixel(4095);   // last pixel
        
        $display("\n========================================");
        $display("Test 3: Monitoring VGA Timing");
        $display("========================================");
        
        // monitor for a few frames
        for (frame_count = 0; frame_count < 3; frame_count = frame_count + 1) begin
            wait(vsync == 0);
            $display("\nFrame %d started", frame_count);
            $display("  h_count: %d, v_count: %d", uut.h_count, uut.v_count);
            
            wait(vsync == 1);
            $display("Frame %d vsync ended", frame_count);
            $display("  h_count: %d, v_count: %d", uut.h_count, uut.v_count);
        end
        
        $display("\n========================================");
        $display("Test 4: Testing Brightness Changes");
        $display("========================================");
        $display("Note: Brightness changes won't affect already processed image");
        $display("      (would need to re-process or reset to see changes)");
        
        brightness = 8'h00;  // minimum
        #10000;
        $display("Brightness = 0x00");
        
        brightness = 8'h20;  // +32
        #10000;
        $display("Brightness = 0x20");
        
        brightness = 8'h0F;  // back to original
        #10000;
        $display("Brightness = 0x0F");
        
        $display("\n========================================");
        $display("Test 5: Sampling Display Output");
        $display("========================================");
        
        // wait for display to be active and sample some pixels
        #1000;
        $display("\nSampling 10 display pixels:");
        for (i = 0; i < 10; i = i + 1) begin
            @(posedge clk);
            if (uut.display_enable) begin
                $display("Display at h=%d, v=%d: R=%h G=%h B=%h (img_addr=%d)", 
                         uut.h_count, uut.v_count, red, green, blue, uut.img_addr);
            end
        end
        
        $display("\n========================================");
        $display("Test Summary");
        $display("========================================");
        $display("ROM Status: %s", (non_zero_count > 0) ? "LOADED" : "EMPTY");
        $display("Non-zero entries: %d / 4096", non_zero_count);
        $display("Processing: %s", uut.processing_done ? "COMPLETE" : "INCOMPLETE");
        $display("Brightness applied: 0x%02h", brightness);
        $display("Frames monitored: %d", frame_count);
        $display("\nAll tests completed!");
        $display("Check waveform viewer for timing details");
        
        #100000;
        
        $finish;
    end
    
    // timeout watchdog
    initial begin
        #50000000; 
        $display("\nERROR: Testbench timeout!");
        $finish;
    end
    
    always @(posedge clk) begin
        if (uut.state == 1) begin  // PROCESS state
            if (uut.process_addr % 512 == 0) begin  
                $display("Processing progress: %d / 4096", uut.process_addr);
            end
        end
    end

endmodule

simulations/tfhe_system/image_controller_tb.vcd
$date
	Mon Nov 24 14:16:42 2025
$end
$version
	Icarus Verilog
$end
$timescale
	1ps
$end
$scope module image_controller_tb $end
$scope module uut $end
$var wire 1 ! hsync $end
$upscope $end
$upscope $end
$scope module image_controller_tb $end
$scope module uut $end
$var wire 1 " vsync $end
$upscope $end
$upscope $end
$scope module image_controller_tb $end
$scope module uut $end
$var wire 4 # red [3:0] $end
$upscope $end
$upscope $end
$scope module image_controller_tb $end
$scope module uut $end
$var wire 4 $ green [3:0] $end
$upscope $end
$upscope $end
$scope module image_controller_tb $end
$scope module uut $end
$var wire 4 % blue [3:0] $end
$upscope $end
$upscope $end
$scope module image_controller_tb $end
$scope module uut $end
$var wire 1 & display_enable $end
$upscope $end
$upscope $end
$enddefinitions $end
$comment Show the parameter values. $end
$dumpall
$end
#0
$dumpvars
1&
b110 %
b110 $
b110 #
1"
1!
$end
#20555000
b0 #
b0 $
b0 %
#25675000
0&
#26315000
0!
#30155000
1!
#32075000
b110 #
b110 $
b110 %
1&
#52555000
b0 #
b0 $
b0 %
#57675000
0&
#58315000
0!
#62155000
1!
#64075000
b110 #
b110 $
b110 %
1&
#84555000
b0 #
b0 $
b0 %
#89675000
0&
#90315000
0!
#94155000
1!
#96075000
b110 #
b110 $
b110 %
1&
#116555000
b0 #
b0 $
b0 %
#121675000
0&
#122315000
0!
#126155000
1!
#128075000
b110 #
b110 $
b110 %
1&
#148555000
b0 #
b0 $
b0 %
#153675000
0&
#154315000
0!
#158155000
1!
#160075000
b110 #
b110 $
b110 %
1&
#180555000
b0 #
b0 $
b0 %
#185675000
0&
#186315000
0!
#190155000
1!
#192075000
b110 #
b110 $
b110 %
1&
#212555000
b0 #
b0 $
b0 %
#217675000
0&
#218315000
0!
#222155000
1!
#224075000
b110 #
b110 $
b110 %
1&
#244555000
b0 #
b0 $
b0 %
#249675000
0&
#250315000
0!
#254155000
1!
#256075000
b110 #
b110 $
b110 %
1&
#259275000
b1101 #
b1101 $
b1101 %
#259595000
b1110 #
b1110 $
b1110 %
#259915000
b1101 #
b1101 $
b1101 %
#260555000
b1100 #
b1100 $
b1100 %
#262475000
b110 #
b110 $
b110 %
#276555000
b0 #
b0 $
b0 %
#281675000
0&
#282315000
0!
#286155000
1!
#288075000
b110 #
b110 $
b110 %
1&
#291275000
b1101 #
b1101 $
b1101 %
#291595000
b1110 #
b1110 $
b1110 %
#291915000
b1101 #
b1101 $
b1101 %
#292555000
b1100 #
b1100 $
b1100 %
#294475000
b110 #
b110 $
b110 %
#308555000
b0 #
b0 $
b0 %
#313675000
0&
#314315000
0!
#318155000
1!
#320075000
b110 #
b110 $
b110 %
1&
#323275000
b1101 #
b1101 $
b1101 %
#323595000
b1110 #
b1110 $
b1110 %
#323915000
b1101 #
b1101 $
b1101 %
#324555000
b1100 #
b1100 $
b1100 %
#326475000
b110 #
b110 $
b110 %
#340555000
b0 #
b0 $
b0 %
#345675000
0&
#346315000
0!
#350155000
1!
#352075000
b110 #
b110 $
b110 %
1&
#355275000
b1101 #
b1101 $
b1101 %
#355595000
b1110 #
b1110 $
b1110 %
#355915000
b1101 #
b1101 $
b1101 %
#356555000
b1100 #
b1100 $
b1100 %
#358475000
b110 #
b110 $
b110 %
#372555000
b0 #
b0 $
b0 %
#377675000
0&
#378315000
0!
#382155000
1!
#384075000
b110 #
b110 $
b110 %
1&
#387275000
b1101 #
b1101 $
b1101 %
#387595000
b1110 #
b1110 $
b1110 %
#387915000
b1101 #
b1101 $
b1101 %
#388555000
b1100 #
b1100 $
b1100 %
#390475000
b110 #
b110 $
b110 %
#404555000
b0 #
b0 $
b0 %
#409675000
0&
#410315000
0!
#414155000
1!
#416075000
b110 #
b110 $
b110 %
1&
#419275000
b1101 #
b1101 $
b1101 %
#419595000
b1110 #
b1110 $
b1110 %
#419915000
b1101 #
b1101 $
b1101 %
#420555000
b1100 #
b1100 $
b1100 %
#422475000
b110 #
b110 $
b110 %
#436555000
b0 #
b0 $
b0 %
#441675000
0&
#442315000
0!
#446155000
1!
#448075000
b110 #
b110 $
b110 %
1&
#451275000
b1101 #
b1101 $
b1101 %
#451595000
b1110 #
b1110 $
b1110 %
#451915000
b1101 #
b1101 $
b1101 %
#452555000
b1100 #
b1100 $
b1100 %
#454475000
b110 #
b110 $
b110 %
#468555000
b0 #
b0 $
b0 %
#473675000
0&
#474315000
0!
#478155000
1!
#480075000
b110 #
b110 $
b110 %
1&
#483275000
b1101 #
b1101 $
b1101 %
#483595000
b1110 #
b1110 $
b1110 %
#483915000
b1101 #
b1101 $
b1101 %
#484555000
b1100 #
b1100 $
b1100 %
#486475000
b110 #
b110 $
b110 %
#500555000
b0 #
b0 $
b0 %
#505675000
0&
#506315000
0!
#510155000
1!
#512075000
b110 #
b110 $
b110 %
1&
#515275000
b1110 #
b1110 $
b1110 %
#515595000
b1111 #
b1111 $
b1111 %
#518795000
b1110 #
b1110 $
b1110 %
#519115000
b1101 #
b1101 $
b1101 %
#519755000
b1100 #
b1100 $
b1100 %
#520715000
b1101 #
b1101 $
b1101 %
#521035000
b1100 #
b1100 $
b1100 %
#521675000
b110 #
b110 $
b110 %
#532555000
b0 #
b0 $
b0 %
#537675000
0&
#538315000
0!
#542155000
1!
#544075000
b110 #
b110 $
b110 %
1&
#547275000
b1110 #
b1110 $
b1110 %
#547595000
b1111 #
b1111 $
b1111 %
#550795000
b1110 #
b1110 $
b1110 %
#551115000
b1101 #
b1101 $
b1101 %
#551755000
b1100 #
b1100 $
b1100 %
#552715000
b1101 #
b1101 $
b1101 %
#553035000
b1100 #
b1100 $
b1100 %
#553675000
b110 #
b110 $
b110 %
#564555000
b0 #
b0 $
b0 %
#569675000
0&
#570315000
0!
#574155000
1!
#576075000
b110 #
b110 $
b110 %
1&
#579275000
b1110 #
b1110 $
b1110 %
#579595000
b1111 #
b1111 $
b1111 %
#582795000
b1110 #
b1110 $
b1110 %
#583115000
b1101 #
b1101 $
b1101 %
#583755000
b1100 #
b1100 $
b1100 %
#584715000
b1101 #
b1101 $
b1101 %
#585035000
b1100 #
b1100 $
b1100 %
#585675000
b110 #
b110 $
b110 %
#596555000
b0 #
b0 $
b0 %
#601675000
0&
#602315000
0!
#606155000
1!
#608075000
b110 #
b110 $
b110 %
1&
#611275000
b1110 #
b1110 $
b1110 %
#611595000
b1111 #
b1111 $
b1111 %
#614795000
b1110 #
b1110 $
b1110 %
#615115000
b1101 #
b1101 $
b1101 %
#615755000
b1100 #
b1100 $
b1100 %
#616715000
b1101 #
b1101 $
b1101 %
#617035000
b1100 #
b1100 $
b1100 %
#617675000
b110 #
b110 $
b110 %
#628555000
b0 #
b0 $
b0 %
#633675000
0&
#634315000
0!
#638155000
1!
#640075000
b110 #
b110 $
b110 %
1&
#643275000
b1110 #
b1110 $
b1110 %
#643595000
b1111 #
b1111 $
b1111 %
#646795000
b1110 #
b1110 $
b1110 %
#647115000
b1101 #
b1101 $
b1101 %
#647755000
b1100 #
b1100 $
b1100 %
#648715000
b1101 #
b1101 $
b1101 %
#649035000
b1100 #
b1100 $
b1100 %
#649675000
b110 #
b110 $
b110 %
#660555000
b0 #
b0 $
b0 %
#665675000
0&
#666315000
0!
#670155000
1!
#672075000
b110 #
b110 $
b110 %
1&
#675275000
b1110 #
b1110 $
b1110 %
#675595000
b1111 #
b1111 $
b1111 %
#678795000
b1110 #
b1110 $
b1110 %
#679115000
b1101 #
b1101 $
b1101 %
#679755000
b1100 #
b1100 $
b1100 %
#680715000
b1101 #
b1101 $
b1101 %
#681035000
b1100 #
b1100 $
b1100 %
#681675000
b110 #
b110 $
b110 %
#692555000
b0 #
b0 $
b0 %
#697675000
0&
#698315000
0!
#702155000
1!
#704075000
b110 #
b110 $
b110 %
1&
#707275000
b1110 #
b1110 $
b1110 %
#707595000
b1111 #
b1111 $
b1111 %
#710795000
b1110 #
b1110 $
b1110 %
#711115000
b1101 #
b1101 $
b1101 %
#711755000
b1100 #
b1100 $
b1100 %
#712715000
b1101 #
b1101 $
b1101 %
#713035000
b1100 #
b1100 $
b1100 %
#713675000
b110 #
b110 $
b110 %
#724555000
b0 #
b0 $
b0 %
#729675000
0&
#730315000
0!
#734155000
1!
#736075000
b110 #
b110 $
b110 %
1&
#739275000
b1110 #
b1110 $
b1110 %
#739595000
b1111 #
b1111 $
b1111 %
#742795000
b1110 #
b1110 $
b1110 %
#743115000
b1101 #
b1101 $
b1101 %
#743755000
b1100 #
b1100 $
b1100 %
#744715000
b1101 #
b1101 $
b1101 %
#745035000
b1100 #
b1100 $
b1100 %
#745675000
b110 #
b110 $
b110 %
#756555000
b0 #
b0 $
b0 %
#761675000
0&
#762315000
0!
#766155000
1!
#768075000
b110 #
b110 $
b110 %
1&
#771275000
b1110 #
b1110 $
b1110 %
#771595000
b1111 #
b1111 $
b1111 %
#777995000
b1110 #
b1110 $
b1110 %
#778315000
b1101 #
b1101 $
b1101 %
#778955000
b1011 #
b1011 $
b1011 %
#779275000
b1100 #
b1100 $
b1100 %
#779915000
b1101 #
b1101 $
b1101 %
#780235000
b1100 #
b1100 $
b1100 %
#780555000
b110 #
b110 $
b110 %
#788555000
b0 #
b0 $
b0 %
#793675000
0&
#794315000
0!
#798155000
1!
#800075000
b110 #
b110 $
b110 %
1&
#803275000
b1110 #
b1110 $
b1110 %
#803595000
b1111 #
b1111 $
b1111 %
#809995000
b1110 #
b1110 $
b1110 %
#810315000
b1101 #
b1101 $
b1101 %
#810955000
b1011 #
b1011 $
b1011 %
#811275000
b1100 #
b1100 $
b1100 %
#811915000
b1101 #
b1101 $
b1101 %
#812235000
b1100 #
b1100 $
b1100 %
#812555000
b110 #
b110 $
b110 %
#820555000
b0 #
b0 $
b0 %
#825675000
0&
#826315000
0!
#830155000
1!
#832075000
b110 #
b110 $
b110 %
1&
#835275000
b1110 #
b1110 $
b1110 %
#835595000
b1111 #
b1111 $
b1111 %
#841995000
b1110 #
b1110 $
b1110 %
#842315000
b1101 #
b1101 $
b1101 %
#842955000
b1011 #
b1011 $
b1011 %
#843275000
b1100 #
b1100 $
b1100 %
#843915000
b1101 #
b1101 $
b1101 %
#844235000
b1100 #
b1100 $
b1100 %
#844555000
b110 #
b110 $
b110 %
#852555000
b0 #
b0 $
b0 %
#857675000
0&
#858315000
0!
#862155000
1!
#864075000
b110 #
b110 $
b110 %
1&
#867275000
b1110 #
b1110 $
b1110 %
#867595000
b1111 #
b1111 $
b1111 %
#873995000
b1110 #
b1110 $
b1110 %
#874315000
b1101 #
b1101 $
b1101 %
#874955000
b1011 #
b1011 $
b1011 %
#875275000
b1100 #
b1100 $
b1100 %
#875915000
b1101 #
b1101 $
b1101 %
#876235000
b1100 #
b1100 $
b1100 %
#876555000
b110 #
b110 $
b110 %
#884555000
b0 #
b0 $
b0 %
#889675000
0&
#890315000
0!
#894155000
1!
#896075000
b110 #
b110 $
b110 %
1&
#899275000
b1110 #
b1110 $
b1110 %
#899595000
b1111 #
b1111 $
b1111 %
#905995000
b1110 #
b1110 $
b1110 %
#906315000
b1101 #
b1101 $
b1101 %
#906955000
b1011 #
b1011 $
b1011 %
#907275000
b1100 #
b1100 $
b1100 %
#907915000
b1101 #
b1101 $
b1101 %
#908235000
b1100 #
b1100 $
b1100 %
#908555000
b110 #
b110 $
b110 %
#916555000
b0 #
b0 $
b0 %
#921675000
0&
#922315000
0!
#926155000
1!
#928075000
b110 #
b110 $
b110 %
1&
#931275000
b1110 #
b1110 $
b1110 %
#931595000
b1111 #
b1111 $
b1111 %
#937995000
b1110 #
b1110 $
b1110 %
#938315000
b1101 #
b1101 $
b1101 %
#938955000
b1011 #
b1011 $
b1011 %
#939275000
b1100 #
b1100 $
b1100 %
#939915000
b1101 #
b1101 $
b1101 %
#940235000
b1100 #
b1100 $
b1100 %
#940555000
b110 #
b110 $
b110 %
#948555000
b0 #
b0 $
b0 %
#953675000
0&
#954315000
0!
#958155000
1!
#960075000
b110 #
b110 $
b110 %
1&
#963275000
b1110 #
b1110 $
b1110 %
#963595000
b1111 #
b1111 $
b1111 %
#969995000
b1110 #
b1110 $
b1110 %
#970315000
b1101 #
b1101 $
b1101 %
#970955000
b1011 #
b1011 $
b1011 %
#971275000
b1100 #
b1100 $
b1100 %
#971915000
b1101 #
b1101 $
b1101 %
#972235000
b1100 #
b1100 $
b1100 %
#972555000
b110 #
b110 $
b110 %
#980555000
b0 #
b0 $
b0 %
#985675000
0&
#986315000
0!
#990155000
1!
#992075000
b110 #
b110 $
b110 %
1&
#995275000
b1110 #
b1110 $
b1110 %
#995595000
b1111 #
b1111 $
b1111 %
#1001995000
b1110 #
b1110 $
b1110 %
#1002315000
b1101 #
b1101 $
b1101 %
#1002955000
b1011 #
b1011 $
b1011 %
#1003275000
b1100 #
b1100 $
b1100 %
#1003915000
b1101 #
b1101 $
b1101 %
#1004235000
b1100 #
b1100 $
b1100 %
#1004555000
b110 #
b110 $
b110 %
#1012555000
b0 #
b0 $
b0 %
#1017675000
0&
#1018315000
0!
#1022155000
1!
#1024075000
b110 #
b110 $
b110 %
1&
#1027275000
b1110 #
b1110 $
b1110 %
#1027595000
b1111 #
b1111 $
b1111 %
#1036875000
b1110 #
b1110 $
b1110 %
#1037195000
b1101 #
b1101 $
b1101 %
#1037835000
b1100 #
b1100 $
b1100 %
#1039755000
b110 #
b110 $
b110 %
#1044555000
b0 #
b0 $
b0 %
#1049675000
0&
#1050315000
0!
#1054155000
1!
#1056075000
b110 #
b110 $
b110 %
1&
#1059275000
b1110 #
b1110 $
b1110 %
#1059595000
b1111 #
b1111 $
b1111 %
#1068875000
b1110 #
b1110 $
b1110 %
#1069195000
b1101 #
b1101 $
b1101 %
#1069835000
b1100 #
b1100 $
b1100 %
#1071755000
b110 #
b110 $
b110 %
#1076555000
b0 #
b0 $
b0 %
#1081675000
0&
#1082315000
0!
#1086155000
1!
#1088075000
b110 #
b110 $
b110 %
1&
#1091275000
b1110 #
b1110 $
b1110 %
#1091595000
b1111 #
b1111 $
b1111 %
#1100875000
b1110 #
b1110 $
b1110 %
#1101195000
b1101 #
b1101 $
b1101 %
#1101835000
b1100 #
b1100 $
b1100 %
#1103755000
b110 #
b110 $
b110 %
#1108555000
b0 #
b0 $
b0 %
#1113675000
0&
#1114315000
0!
#1118155000
1!
#1120075000
b110 #
b110 $
b110 %
1&
#1123275000
b1110 #
b1110 $
b1110 %
#1123595000
b1111 #
b1111 $
b1111 %
#1132875000
b1110 #
b1110 $
b1110 %
#1133195000
b1101 #
b1101 $
b1101 %
#1133835000
b1100 #
b1100 $
b1100 %
#1135755000
b110 #
b110 $
b110 %
#1140555000
b0 #
b0 $
b0 %
#1145675000
0&
#1146315000
0!
#1150155000
1!
#1152075000
b110 #
b110 $
b110 %
1&
#1155275000
b1110 #
b1110 $
b1110 %
#1155595000
b1111 #
b1111 $
b1111 %
#1164875000
b1110 #
b1110 $
b1110 %
#1165195000
b1101 #
b1101 $
b1101 %
#1165835000
b1100 #
b1100 $
b1100 %
#1167755000
b110 #
b110 $
b110 %
#1172555000
b0 #
b0 $
b0 %
#1177675000
0&
#1178315000
0!
#1182155000
1!
#1184075000
b110 #
b110 $
b110 %
1&
#1187275000
b1110 #
b1110 $
b1110 %
#1187595000
b1111 #
b1111 $
b1111 %
#1196875000
b1110 #
b1110 $
b1110 %
#1197195000
b1101 #
b1101 $
b1101 %
#1197835000
b1100 #
b1100 $
b1100 %
#1199755000
b110 #
b110 $
b110 %
#1204555000
b0 #
b0 $
b0 %
#1209675000
0&
#1210315000
0!
#1214155000
1!
#1216075000
b110 #
b110 $
b110 %
1&
#1219275000
b1110 #
b1110 $
b1110 %
#1219595000
b1111 #
b1111 $
b1111 %
#1228875000
b1110 #
b1110 $
b1110 %
#1229195000
b1101 #
b1101 $
b1101 %
#1229835000
b1100 #
b1100 $
b1100 %
#1231755000
b110 #
b110 $
b110 %
#1236555000
b0 #
b0 $
b0 %
#1241675000
0&
#1242315000
0!
#1246155000
1!
#1248075000
b110 #
b110 $
b110 %
1&
#1251275000
b1110 #
b1110 $
b1110 %
#1251595000
b1111 #
b1111 $
b1111 %
#1260875000
b1110 #
b1110 $
b1110 %
#1261195000
b1101 #
b1101 $
b1101 %
#1261835000
b1100 #
b1100 $
b1100 %
#1263755000
b110 #
b110 $
b110 %
#1268555000
b0 #
b0 $
b0 %
#1273675000
0&
#1274315000
0!
#1278155000
1!
#1280075000
b110 #
b110 $
b110 %
1&
#1283275000
b1110 #
b1110 $
b1110 %
#1283595000
b1111 #
b1111 $
b1111 %
#1284235000
b1101 #
b1101 $
b1101 %
#1284555000
b1111 #
b1111 $
b1111 %
#1296075000
b1110 #
b1110 $
b1110 %
#1296395000
b1101 #
b1101 $
b1101 %
#1297035000
b1100 #
b1100 $
b1100 %
#1297355000
b110 #
b110 $
b110 %
#1300555000
b0 #
b0 $
b0 %
#1305675000
0&
#1306315000
0!
#1310155000
1!
